easy_raster/__init__.py
easy_raster/model/__init__.py
easy_raster/model/position.py
easy_raster/model/resolution.py
easy_raster/raster_io.py
easy_raster/transform/__init__.py
easy_raster/transform/buffer_util.py
easy_raster/transform/morphology.py
easy_raster/transform/normalizer.py
easy_raster/utils/__init__.py
easy_raster/utils/factory.py
easy_raster/utils/float_utils.py
easy_raster/utils/video_utils.py
easy_raster-0.1.2.dist-info/METADATA
easy_raster-0.1.2.dist-info/WHEEL
easy_raster-0.1.2.dist-info/RECORD
