Metadata-Version: 2.1
Name: easy-raster
Version: 0.1.2
Summary: Easy to use raster operations
Home-page: https://github.com/flegac/easy-raster
License: MIT
Author: flegac
Author-email: florent.legac@gmail.com
Requires-Python: >=3.10,<4.0
Classifier: License :: OSI Approved :: MIT License
Classifier: Operating System :: OS Independent
Classifier: Programming Language :: Python :: 3
Classifier: Programming Language :: Python :: 3.10
Classifier: Programming Language :: Python :: 3.11
Classifier: Programming Language :: Python :: 3.12
Requires-Dist: easy-kit (==0.0.4)
Requires-Dist: ffmpeg-python (==0.2.0)
Requires-Dist: rasterio (==1.3.10)
Requires-Dist: scikit-image (==0.24.0)
Requires-Dist: scipy (>=1.14.1,<2.0.0)
Project-URL: Repository, https://github.com/flegac/easy-raster
